rmc/__init__.py
rmc/cli.py
rmc/exporters/markdown.py
rmc/exporters/pdf.py
rmc/exporters/svg.py
rmc/exporters/writing_tools.py
rmc/py.typed
rmc-0.3.0.dist-info/LICENSE
rmc-0.3.0.dist-info/METADATA
rmc-0.3.0.dist-info/WHEEL
rmc-0.3.0.dist-info/entry_points.txt
rmc-0.3.0.dist-info/RECORD
